{
  "name": "Invenicum Official Store",
  "description": "Repositorio oficial de extensiones",
  "plugins": [
    {
      "id": "reloj_digital_01",
      "name": "Reloj Digital",
      "version": "1.0.0",
      "description": "Muestra un reloj elegante en tu dashboard.",
      "author": "Invenicum Team",
      "isOfficial": true, 
      "icon_url": "https://raw.githubusercontent.com/lopiv2/invenicum-plugin-repository/main/assets/reloj_icon.png",
      "download_url": "https://https://raw.githubusercontent.com/lopiv2/invenicum-plugin-repository/main/plugins/Reloj%20Digital.json"
    }
  ]
}
